{"nodes": [{"id": "d_10_leochad_pzmciphertool_backendcipher_aliyunsmsmd_aliyunsmsbackend_plan_md", "label": "ALIYUNSMSbackend_PLAN.md", "file_type": "document", "source_file": "D:\\10_Leochad\\PzMCiphertool-\\backendcipher\\Aliyunsmsmd\\ALIYUNSMSbackend_PLAN.md", "source_location": "L1"}, {"id": "aliyunsmsmd_aliyunsmsbackend_plan_ciphertool_\u540e\u7aef\u5f00\u53d1\u8ba1\u5212", "label": "CipherTool \u540e\u7aef\u5f00\u53d1\u8ba1\u5212", "file_type": "document", "source_file": "D:\\10_Leochad\\PzMCiphertool-\\backendcipher\\Aliyunsmsmd\\ALIYUNSMSbackend_PLAN.md", "source_location": "L1"}, {"id": "aliyunsmsmd_aliyunsmsbackend_plan_\u4e00_\u9879\u76ee\u6982\u8ff0", "label": "\u4e00\u3001\u9879\u76ee\u6982\u8ff0", "file_type": "document", "source_file": "D:\\10_Leochad\\PzMCiphertool-\\backendcipher\\Aliyunsmsmd\\ALIYUNSMSbackend_PLAN.md", "source_location": "L3"}, {"id": "aliyunsmsmd_aliyunsmsbackend_plan_\u4e8c_\u6280\u672f\u6808", "label": "\u4e8c\u3001\u6280\u672f\u6808", "file_type": "document", "source_file": "D:\\10_Leochad\\PzMCiphertool-\\backendcipher\\Aliyunsmsmd\\ALIYUNSMSbackend_PLAN.md", "source_location": "L9"}, {"id": "aliyunsmsmd_aliyunsmsbackend_plan_\u4e09_\u9879\u76ee\u7ed3\u6784", "label": "\u4e09\u3001\u9879\u76ee\u7ed3\u6784", "file_type": "document", "source_file": "D:\\10_Leochad\\PzMCiphertool-\\backendcipher\\Aliyunsmsmd\\ALIYUNSMSbackend_PLAN.md", "source_location": "L21"}, {"id": "aliyunsmsmd_aliyunsmsbackend_plan_\u56db_api_\u8bbe\u8ba1", "label": "\u56db\u3001API \u8bbe\u8ba1", "file_type": "document", "source_file": "D:\\10_Leochad\\PzMCiphertool-\\backendcipher\\Aliyunsmsmd\\ALIYUNSMSbackend_PLAN.md", "source_location": "L54"}, {"id": "aliyunsmsmd_aliyunsmsbackend_plan_1_\u53d1\u9001\u9a8c\u8bc1\u7801", "label": "1. \u53d1\u9001\u9a8c\u8bc1\u7801", "file_type": "document", "source_file": "D:\\10_Leochad\\PzMCiphertool-\\backendcipher\\Aliyunsmsmd\\ALIYUNSMSbackend_PLAN.md", "source_location": "L56"}, {"id": "aliyunsmsmd_aliyunsmsbackend_plan_2_\u767b\u5f55\u9a8c\u8bc1", "label": "2. \u767b\u5f55\u9a8c\u8bc1", "file_type": "document", "source_file": "D:\\10_Leochad\\PzMCiphertool-\\backendcipher\\Aliyunsmsmd\\ALIYUNSMSbackend_PLAN.md", "source_location": "L79"}, {"id": "aliyunsmsmd_aliyunsmsbackend_plan_3_\u68c0\u67e5\u767b\u5f55\u72b6\u6001", "label": "3. \u68c0\u67e5\u767b\u5f55\u72b6\u6001", "file_type": "document", "source_file": "D:\\10_Leochad\\PzMCiphertool-\\backendcipher\\Aliyunsmsmd\\ALIYUNSMSbackend_PLAN.md", "source_location": "L101"}, {"id": "aliyunsmsmd_aliyunsmsbackend_plan_\u4e94_redis_\u6570\u636e\u7ed3\u6784", "label": "\u4e94\u3001Redis \u6570\u636e\u7ed3\u6784", "file_type": "document", "source_file": "D:\\10_Leochad\\PzMCiphertool-\\backendcipher\\Aliyunsmsmd\\ALIYUNSMSbackend_PLAN.md", "source_location": "L108"}, {"id": "aliyunsmsmd_aliyunsmsbackend_plan_\u516d_\u5b89\u5168\u63aa\u65bd", "label": "\u516d\u3001\u5b89\u5168\u63aa\u65bd", "file_type": "document", "source_file": "D:\\10_Leochad\\PzMCiphertool-\\backendcipher\\Aliyunsmsmd\\ALIYUNSMSbackend_PLAN.md", "source_location": "L118"}, {"id": "aliyunsmsmd_aliyunsmsbackend_plan_\u4e03_\u5f00\u53d1\u6b65\u9aa4", "label": "\u4e03\u3001\u5f00\u53d1\u6b65\u9aa4", "file_type": "document", "source_file": "D:\\10_Leochad\\PzMCiphertool-\\backendcipher\\Aliyunsmsmd\\ALIYUNSMSbackend_PLAN.md", "source_location": "L134"}, {"id": "aliyunsmsmd_aliyunsmsbackend_plan_\u516b_\u914d\u7f6e\u9879_application_yml", "label": "\u516b\u3001\u914d\u7f6e\u9879 (application.yml)", "file_type": "document", "source_file": "D:\\10_Leochad\\PzMCiphertool-\\backendcipher\\Aliyunsmsmd\\ALIYUNSMSbackend_PLAN.md", "source_location": "L146"}, {"id": "aliyunsmsmd_aliyunsmsbackend_plan_\u4e5d_\u6ce8\u610f\u4e8b\u9879", "label": "\u4e5d\u3001\u6ce8\u610f\u4e8b\u9879", "file_type": "document", "source_file": "D:\\10_Leochad\\PzMCiphertool-\\backendcipher\\Aliyunsmsmd\\ALIYUNSMSbackend_PLAN.md", "source_location": "L168"}], "edges": [{"source": "d_10_leochad_pzmciphertool_backendcipher_aliyunsmsmd_aliyunsmsbackend_plan_md", "target": "aliyunsmsmd_aliyunsmsbackend_plan_ciphertool_\u540e\u7aef\u5f00\u53d1\u8ba1\u5212", "relation": "contains", "confidence": "EXTRACTED", "source_file": "D:\\10_Leochad\\PzMCiphertool-\\backendcipher\\Aliyunsmsmd\\ALIYUNSMSbackend_PLAN.md", "source_location": "L1", "weight": 1.0}, {"source": "aliyunsmsmd_aliyunsmsbackend_plan_ciphertool_\u540e\u7aef\u5f00\u53d1\u8ba1\u5212", "target": "aliyunsmsmd_aliyunsmsbackend_plan_\u4e00_\u9879\u76ee\u6982\u8ff0", "relation": "contains", "confidence": "EXTRACTED", "source_file": "D:\\10_Leochad\\PzMCiphertool-\\backendcipher\\Aliyunsmsmd\\ALIYUNSMSbackend_PLAN.md", "source_location": "L3", "weight": 1.0}, {"source": "aliyunsmsmd_aliyunsmsbackend_plan_ciphertool_\u540e\u7aef\u5f00\u53d1\u8ba1\u5212", "target": "aliyunsmsmd_aliyunsmsbackend_plan_\u4e8c_\u6280\u672f\u6808", "relation": "contains", "confidence": "EXTRACTED", "source_file": "D:\\10_Leochad\\PzMCiphertool-\\backendcipher\\Aliyunsmsmd\\ALIYUNSMSbackend_PLAN.md", "source_location": "L9", "weight": 1.0}, {"source": "aliyunsmsmd_aliyunsmsbackend_plan_ciphertool_\u540e\u7aef\u5f00\u53d1\u8ba1\u5212", "target": "aliyunsmsmd_aliyunsmsbackend_plan_\u4e09_\u9879\u76ee\u7ed3\u6784", "relation": "contains", "confidence": "EXTRACTED", "source_file": "D:\\10_Leochad\\PzMCiphertool-\\backendcipher\\Aliyunsmsmd\\ALIYUNSMSbackend_PLAN.md", "source_location": "L21", "weight": 1.0}, {"source": "aliyunsmsmd_aliyunsmsbackend_plan_ciphertool_\u540e\u7aef\u5f00\u53d1\u8ba1\u5212", "target": "aliyunsmsmd_aliyunsmsbackend_plan_\u56db_api_\u8bbe\u8ba1", "relation": "contains", "confidence": "EXTRACTED", "source_file": "D:\\10_Leochad\\PzMCiphertool-\\backendcipher\\Aliyunsmsmd\\ALIYUNSMSbackend_PLAN.md", "source_location": "L54", "weight": 1.0}, {"source": "aliyunsmsmd_aliyunsmsbackend_plan_\u56db_api_\u8bbe\u8ba1", "target": "aliyunsmsmd_aliyunsmsbackend_plan_1_\u53d1\u9001\u9a8c\u8bc1\u7801", "relation": "contains", "confidence": "EXTRACTED", "source_file": "D:\\10_Leochad\\PzMCiphertool-\\backendcipher\\Aliyunsmsmd\\ALIYUNSMSbackend_PLAN.md", "source_location": "L56", "weight": 1.0}, {"source": "aliyunsmsmd_aliyunsmsbackend_plan_\u56db_api_\u8bbe\u8ba1", "target": "aliyunsmsmd_aliyunsmsbackend_plan_2_\u767b\u5f55\u9a8c\u8bc1", "relation": "contains", "confidence": "EXTRACTED", "source_file": "D:\\10_Leochad\\PzMCiphertool-\\backendcipher\\Aliyunsmsmd\\ALIYUNSMSbackend_PLAN.md", "source_location": "L79", "weight": 1.0}, {"source": "aliyunsmsmd_aliyunsmsbackend_plan_\u56db_api_\u8bbe\u8ba1", "target": "aliyunsmsmd_aliyunsmsbackend_plan_3_\u68c0\u67e5\u767b\u5f55\u72b6\u6001", "relation": "contains", "confidence": "EXTRACTED", "source_file": "D:\\10_Leochad\\PzMCiphertool-\\backendcipher\\Aliyunsmsmd\\ALIYUNSMSbackend_PLAN.md", "source_location": "L101", "weight": 1.0}, {"source": "aliyunsmsmd_aliyunsmsbackend_plan_ciphertool_\u540e\u7aef\u5f00\u53d1\u8ba1\u5212", "target": "aliyunsmsmd_aliyunsmsbackend_plan_\u4e94_redis_\u6570\u636e\u7ed3\u6784", "relation": "contains", "confidence": "EXTRACTED", "source_file": "D:\\10_Leochad\\PzMCiphertool-\\backendcipher\\Aliyunsmsmd\\ALIYUNSMSbackend_PLAN.md", "source_location": "L108", "weight": 1.0}, {"source": "aliyunsmsmd_aliyunsmsbackend_plan_ciphertool_\u540e\u7aef\u5f00\u53d1\u8ba1\u5212", "target": "aliyunsmsmd_aliyunsmsbackend_plan_\u516d_\u5b89\u5168\u63aa\u65bd", "relation": "contains", "confidence": "EXTRACTED", "source_file": "D:\\10_Leochad\\PzMCiphertool-\\backendcipher\\Aliyunsmsmd\\ALIYUNSMSbackend_PLAN.md", "source_location": "L118", "weight": 1.0}, {"source": "aliyunsmsmd_aliyunsmsbackend_plan_ciphertool_\u540e\u7aef\u5f00\u53d1\u8ba1\u5212", "target": "aliyunsmsmd_aliyunsmsbackend_plan_\u4e03_\u5f00\u53d1\u6b65\u9aa4", "relation": "contains", "confidence": "EXTRACTED", "source_file": "D:\\10_Leochad\\PzMCiphertool-\\backendcipher\\Aliyunsmsmd\\ALIYUNSMSbackend_PLAN.md", "source_location": "L134", "weight": 1.0}, {"source": "aliyunsmsmd_aliyunsmsbackend_plan_ciphertool_\u540e\u7aef\u5f00\u53d1\u8ba1\u5212", "target": "aliyunsmsmd_aliyunsmsbackend_plan_\u516b_\u914d\u7f6e\u9879_application_yml", "relation": "contains", "confidence": "EXTRACTED", "source_file": "D:\\10_Leochad\\PzMCiphertool-\\backendcipher\\Aliyunsmsmd\\ALIYUNSMSbackend_PLAN.md", "source_location": "L146", "weight": 1.0}, {"source": "aliyunsmsmd_aliyunsmsbackend_plan_ciphertool_\u540e\u7aef\u5f00\u53d1\u8ba1\u5212", "target": "aliyunsmsmd_aliyunsmsbackend_plan_\u4e5d_\u6ce8\u610f\u4e8b\u9879", "relation": "contains", "confidence": "EXTRACTED", "source_file": "D:\\10_Leochad\\PzMCiphertool-\\backendcipher\\Aliyunsmsmd\\ALIYUNSMSbackend_PLAN.md", "source_location": "L168", "weight": 1.0}], "input_tokens": 0, "output_tokens": 0}